{
    "arr":
    [
        {"context":"怕目光夹杂爱意 所以不敢看你. ","link":"https://v.douyin.com/ekKVwNk/"},
        {"context":"总有一场相遇，是互相喜欢 ","link":"https://v.douyin.com/ekN88xJ/"},
        {"context":"你闯进我的镜头，我按下了永远。 ","link":null},
        {"context":"欲言又止就是答案 答非所问也是 ","link":"https://v.douyin.com/eMvBqPV/"},
        {"context":"大院门口的狗又老了一岁 站都站不稳了 有时间回去看看吧 院子都黄了 ","link":null},
        {"context":"当产生丁达尔效应的时候 光就有了形状 亦如光明中的你 把我拉出了黑暗 ","link":"https://v.douyin.com/eN54exw/"},
        {"context":"相遇不一定有结局，但一定有意义，再见容易，再见却很难，愿所有美好如约而至。 ","link":"https://v.douyin.com/e8RqepV/"},
        {"context":"趁着月亮和星星都在 悄悄的说声 我喜欢你 ","link":"https://www.iesdouyin.com/share/video/6937627263508761892/"},
        {"context":"我们会在无数个夏天的风里继续相见 ","link":"https://v.douyin.com/eebdryE/"},
        {"context":"身边人这么暖，求助一下又何妨 ","link":null},
        {"context":"再过几天，如果有一个白胡子的老头，把你打晕了装在麻袋里，别害怕，因为……我的圣诞愿望是你. ","link":"https://v.douyin.com/Jqnxd8U/"},
        {"context":"我是圣诞老人：由于疫情进入中国需要隔离，所以我已进入国内，为防止袜子中放错礼物，女生们请把穿袜子腿照发我 ","link":"https://v.douyin.com/JqgC4vp/"},
        {"context":"你轻松拒绝掉那个非常喜欢你的人，也是别人梦寐以求的心上人， 你苦苦追求不到的心上人，在另一个人那里也很卑微 ","link":"https://v.douyin.com/J4DwFPv/"},
        {"context":"所有的遗憾和错过你相比，都是一种幸运 ","link":null},
        {"context":"靠近光 追随光 成为光 发散光 ","link":"https://v.douyin.com/Jx3nR9A/"},
        {"context":"时间不会让我忘了你，只会习惯让我没有你，我仍对你难以忘怀，但不再对你满怀期待，有的人终究是可望，可念，不可及. ","link":"https://v.douyin.com/J9v1GeT/"},
        {"context":"夏天的名字叫七里香，秋天的名字叫枫 ","link":"https://v.douyin.com/JHDW5r6/"},
        {"context":"青春是昏睡与暗恋交织的夏天 ","link":null},
        {"context":"慢慢来吧，我一直陪你，你很可爱 不止可爱 也值得被爱 ","link":"https://v.douyin.com/JHjgV9h/"},
        {"context":"你今天看起来真漂亮 ","link":null},
        {"context":"你的声音最好听，你身上的味道最好闻，你笑起来的样子最好看，你陪着我的时候，我从没羡慕过谁，我喜欢你所有的样子 ","link":null},
        {"context":"如果可以的话，以后我们一起逛超市，陪你逛街，一起看电影，一起喝奶茶，一起生活，一起走完剩下的路. ","link":"https://v.douyin.com/JHFhqgM/"},
        {"context":"我本可以努力，但世界上最无用的一句话便是我本可以。 ","link":null},
        {"context":"做喜欢的事情从来都不是浪费时间 ","link":"https://v.douyin.com/JuKuq5p/"},
        {"context":"三观只是为了约束自己而不是审视他人 ","link":"https://v.douyin.com/JuwR9yT/"},
        {"context":"当我的手指划过尺子的3和4刻度之间时我是否触摸到π 当我的手指抚摸到地球仪上的那个城市时 我是否触摸到你 ","link":null},
        {"context":"把普通的日子过得浪漫些 我的意思是和你 ","link":null},
        {"context":"其实早就跟你表白过了，在看你的每一个眼神里 ","link":"https://v.douyin.com/JuyQG8G/"},
        {"context":"天空偷喝了我放在屋顶的红酒，醉了臆想，红了脸颊，成了晚霞，偷看着这世间温柔的万物 ","link":"https://v.douyin.com/JuyYtpP/"},
        {"context":"人总是在接近幸福的时候倍感幸福，在幸福进行却患得患失。 ","link":"https://v.douyin.com/JmrnNE5/"},
        {"context":"总是嚷嚷着要找对象，但从不主动勾搭，却羡慕别人成双成对，你到底在等谁？ ","link":"https://v.douyin.com/JPjFB4B/"},
        {"context":"有些人，遇见即是幸运。 ","link":"https://v.douyin.com/JftBXQU/"},
        {"context":"光是遇见，就已经很美好了💗 ","link":"https://v.douyin.com/JfrwFWq/"},
        {"context":"只为了更好遇见，才赋予了距离和时间。那一天，值得等待；那一眼，满载星海。 ","link":"https://v.douyin.com/JyQ7hXN/"},
        {"context":"我现在不知道怎么关心你了，你有很多朋友，过着比我精彩的生活，每天都很开心，而我的生活好像只有你，却没有你 ","link":"https://v.douyin.com/JyCJnYR/"},
        {"context":"你是我的单曲循环，我是你的随机播放，这句话再合适不过了 ","link":"https://v.douyin.com/JyQ7aGx/"},
        {"context":"如果我们有机会仰望同一片天空，你看天空，我看你，我们在天空下，你在我心上 ","link":"https://v.douyin.com/Jyh7sCJ/"},
        {"context":"假装没看见 却用余光看过千遍  ","link":"https://v.douyin.com/JyMMhTK/"},
        {"context":"心理学上说：我们故意避开的人，往往都是很在意的人，下意识躲开是因为紧张，回头看是因为喜欢抖 ","link":"https://v.douyin.com/JU82p2a/"},
        {"context":"你要相信，世界上总有一个人愿意用最朴素的方式爱你，不是撩你，也不是套路，就是单纯的想对你好，忍不住的那种 ","link":"https://v.douyin.com/JU86qm6/"},
        {"context":"今天看到一句话很触动：今年的国庆和中秋是来弥补春节的遗憾的。两天后，国兴，家睦，月明。❤️ ","link":"https://v.douyin.com/JDnE44K/"},
        {"context":"面无表情的擦肩而过都是装的，但回头看你是真的 ","link":"https://v.douyin.com/JDqc1Q3/"},
        {"context":"突然很喜欢惊鸿一瞥这个词，一见钟情太肤浅了，日久生情太苍白，别人眉来眼去，我呀 只偷看你一眼 ","link":"https://v.douyin.com/JDACQAd/"},
        {"context":"秋不秋天我不知道 反正该黄的都黄了，搓搓手又要一个人过冬天了 ","link":"https://v.douyin.com/JDjGcQh/"},
        {"context":"暗恋是什么？是那天窗外下雨，你没看我，我没看雨，暗恋是目光所及时，那害羞躲闪的眼神。 ","link":null},
        {"context":"我存过你的照片儿。你喜欢的歌我也去听过你看过的电影我也偷偷的看过。你感兴趣过的东西我也尝试感兴趣过。我远比表面更喜欢你后来我瞒着所有人的面喜欢你。没有人知道。包括你。 ","link":null},
        {"context":"遇见你是一件很幸运的事情. ","link":"https://v.douyin.com/JSTwTdW/"},
        {"context":"突然想起你，才发现除了你的名字，我记不清你的长相，想不起你的声音，甚至连我们的过往都忘的差不多了 ","link":"https://v.douyin.com/JSw8rPh/"},
        {"context":"刷到一个很棒的文案:丧太简单了，顶着一切依旧热爱生活才是真的酷，祝我们都能在鸡零狗碎的生活里找到自己的快乐。 ","link":"https://v.douyin.com/JSfQuf9/"},
        {"context":"我一个吃棒棒糖都要咬着吃的人，倘若不喜欢你，谁又天天陪你谈心呀 ","link":null},
        {"context":"人生最大的遗憾不是你错过了最好的人，而是你错过了最想对你好的人。 ","link":"https://v.douyin.com/J2BqtFB/"},
        {"context":"我今天发现了个事 喜羊羊的爸爸是智羊羊 欢乐颂的作者是贝多芬 你能发现这是藏头诗吗 ","link":"https://v.douyin.com/J2SLyrT/"},
        {"context":"知道未来没有你，我好像也没有那么着急的往前走了 ","link":"https://v.douyin.com/Jjo9J4m/"},
        {"context":"快去等艾特你喜欢的人吧 ","link":"https://v.douyin.com/J6RLMwG/"},
        {"context":"山水一程,风雨一更,三生有幸,共度余生 ","link":"https://v.douyin.com/JMevaQA/"},
        {"context":"如何把晚安说的高逼格一点：山河已暮，时已寝安；虽不同枕，但求同梦 ","link":"https://v.douyin.com/JMe3Vxv/"},
        {"context":"那个每天偷偷看你各种动态，偷偷看你头像，偷偷看你抖音喜欢的人，他比任何人都爱你，只是再无身份联系 ","link":"https://v.douyin.com/JBdj6A9/"},
        {"context":"你眼里装的是这天下，而我的眼里只有你！ ","link":"https://v.douyin.com/JB4nGWx/"}
    ]
}

